metering/__init__.py
metering/constants.py
metering/customer.py
metering/customer_portal_session.py
metering/customer_prepaid_order.py
metering/customer_product_invoice.py
metering/customer_product_plan.py
metering/exceptions.py
metering/llms.py
metering/usage.py
metering/validators.py
metering/version.py
metering/ingest/__init__.py
metering/ingest/api_client.py
metering/ingest/consumer.py
metering/ingest/producer.py
metering/ingest/s3_client.py
metering/session/__init__.py
metering/session/api_session.py
metering/session/ingest_session.py
amberflo_metering_python-3.3.1.dist-info/LICENSE
amberflo_metering_python-3.3.1.dist-info/METADATA
amberflo_metering_python-3.3.1.dist-info/WHEEL
amberflo_metering_python-3.3.1.dist-info/top_level.txt
amberflo_metering_python-3.3.1.dist-info/RECORD
