Metadata-Version: 2.1
Name: amberflo-metering-python
Version: 3.3.1
Summary: Integrate Amberflo into any Python 3 application.
Home-page: https://github.com/amberflo/metering-python
Author: Amberflo
Author-email: friends@amberflo.com
Maintainer: Amberflo.io
Maintainer-email: friends@amberflo.com
License: MIT License
Platform: UNKNOWN
Classifier: Development Status :: 5 - Production/Stable
Classifier: Intended Audience :: Developers
Classifier: License :: OSI Approved :: MIT License
Classifier: Operating System :: OS Independent
Classifier: Programming Language :: Python :: 3.6
Classifier: Programming Language :: Python :: 3.7
Classifier: Programming Language :: Python :: 3.8
Classifier: Programming Language :: Python :: 3.9
Classifier: Programming Language :: Python :: 3.10
Requires-Dist: requests
Requires-Dist: backoff
Provides-Extra: openai
Requires-Dist: openai; extra == "openai"
Provides-Extra: s3
Requires-Dist: boto3; extra == "s3"
